bijux_rag/__init__.py
bijux_rag/_version.py
bijux_rag/py.typed
bijux_rag/boundaries/__init__.py
bijux_rag/boundaries/app_config.py
bijux_rag/boundaries/adapters/__init__.py
bijux_rag/boundaries/adapters/exception_bridge.py
bijux_rag/boundaries/adapters/pydantic_edges.py
bijux_rag/boundaries/adapters/serde.py
bijux_rag/boundaries/shells/__init__.py
bijux_rag/boundaries/shells/cli.py
bijux_rag/boundaries/shells/rag_api_shell.py
bijux_rag/boundaries/shells/rag_file_shell.py
bijux_rag/boundaries/shells/rag_main.py
bijux_rag/boundaries/shells/typer_cli.py
bijux_rag/boundaries/web/__init__.py
bijux_rag/boundaries/web/fastapi_app.py
bijux_rag/core/__init__.py
bijux_rag/core/rag_types.py
bijux_rag/core/rules_dsl.py
bijux_rag/core/rules_lint.py
bijux_rag/core/rules_pred.py
bijux_rag/core/structural_dedup.py
bijux_rag/domain/__init__.py
bijux_rag/domain/capabilities.py
bijux_rag/domain/composition.py
bijux_rag/domain/facades.py
bijux_rag/domain/idempotent.py
bijux_rag/domain/logging.py
bijux_rag/domain/effects/__init__.py
bijux_rag/domain/effects/io_plan.py
bijux_rag/domain/effects/io_retry.py
bijux_rag/domain/effects/tx.py
bijux_rag/domain/effects/async_/__init__.py
bijux_rag/domain/effects/async_/concurrency.py
bijux_rag/domain/effects/async_/plan.py
bijux_rag/domain/effects/async_/resilience.py
bijux_rag/domain/effects/async_/stream.py
bijux_rag/fp/__init__.py
bijux_rag/fp/applicative.py
bijux_rag/fp/combinators.py
bijux_rag/fp/core.py
bijux_rag/fp/error.py
bijux_rag/fp/functor.py
bijux_rag/fp/monoid.py
bijux_rag/fp/option_result.py
bijux_rag/fp/validation.py
bijux_rag/fp/effects/__init__.py
bijux_rag/fp/effects/configurable.py
bijux_rag/fp/effects/layering.py
bijux_rag/fp/effects/reader.py
bijux_rag/fp/effects/state.py
bijux_rag/fp/effects/writer.py
bijux_rag/infra/__init__.py
bijux_rag/infra/adapters/__init__.py
bijux_rag/infra/adapters/async_runtime.py
bijux_rag/infra/adapters/atomic_storage.py
bijux_rag/infra/adapters/clock.py
bijux_rag/infra/adapters/file_storage.py
bijux_rag-0.1.0.dist-info/METADATA
bijux_rag-0.1.0.dist-info/WHEEL
bijux_rag-0.1.0.dist-info/entry_points.txt
bijux_rag-0.1.0.dist-info/licenses/LICENSE
bijux_rag-0.1.0.dist-info/RECORD
