Metadata-Version: 2.4
Name: bijux-rag
Version: 0.1.0
Summary: Standalone Bijux RAG toolkit
Project-URL: Homepage, https://github.com/bijux/bijux-rag
Project-URL: Repository, https://github.com/bijux/bijux-rag.git
Project-URL: BugTracker, https://github.com/bijux/bijux-rag/issues
Author-email: Bijan Mousavi <mousavi.bijan@gmail.com>
License: MIT
License-File: LICENSE
Classifier: License :: OSI Approved :: MIT License
Classifier: Programming Language :: Python :: 3
Classifier: Programming Language :: Python :: 3.11
Classifier: Programming Language :: Python :: 3.12
Classifier: Programming Language :: Python :: 3.13
Classifier: Topic :: Scientific/Engineering :: Information Analysis
Classifier: Typing :: Typed
Requires-Python: <4.0,>=3.11
Requires-Dist: fastapi<1.0,>=0.115
Requires-Dist: msgpack<2,>=1.0
Requires-Dist: numpy<3,>=1.26
Requires-Dist: pydantic<3,>=2.7
Requires-Dist: pyyaml<7,>=6
Requires-Dist: typing-extensions<5,>=4.9
Requires-Dist: uvicorn<1.0,>=0.32
Provides-Extra: dev
Requires-Dist: bandit<2.0,>=1.7.10; extra == 'dev'
Requires-Dist: build<2.0,>=1.2; extra == 'dev'
Requires-Dist: deptry<1.0,>=0.10.0; extra == 'dev'
Requires-Dist: hypothesis<7.0,>=6.91; extra == 'dev'
Requires-Dist: interrogate<2.0,>=1.7.0; extra == 'dev'
Requires-Dist: mkdocs-click<1,>=0.8; extra == 'dev'
Requires-Dist: mkdocs-gen-files<1,>=0.5; extra == 'dev'
Requires-Dist: mkdocs-git-revision-date-localized-plugin<2,>=1.2; extra == 'dev'
Requires-Dist: mkdocs-glightbox>=0.4.0; extra == 'dev'
Requires-Dist: mkdocs-include-markdown-plugin; extra == 'dev'
Requires-Dist: mkdocs-literate-nav<1,>=0.6; extra == 'dev'
Requires-Dist: mkdocs-material<10,>=9.5; extra == 'dev'
Requires-Dist: mkdocs-minify-plugin<1,>=0.8; extra == 'dev'
Requires-Dist: mkdocs-redirects<2,>=1.2; extra == 'dev'
Requires-Dist: mkdocs-section-index<1,>=0.3; extra == 'dev'
Requires-Dist: mkdocs<2,>=1.6; extra == 'dev'
Requires-Dist: mkdocstrings[python]<1,>=0.29; extra == 'dev'
Requires-Dist: mypy<2.0,>=1.11; extra == 'dev'
Requires-Dist: openapi-spec-validator<1.0,>=0.7.1; extra == 'dev'
Requires-Dist: pip-audit<3.0,>=2.7.3; extra == 'dev'
Requires-Dist: prance>=25.4.0.0; extra == 'dev'
Requires-Dist: pymdown-extensions<11,>=10.8; extra == 'dev'
Requires-Dist: pyright<2.0,>=1.1.380; extra == 'dev'
Requires-Dist: pyright[nodejs]<2.0,>=1.1.380; extra == 'dev'
Requires-Dist: pytest-asyncio<1.0,>=0.23; extra == 'dev'
Requires-Dist: pytest-cov<7.0,>=6.0; extra == 'dev'
Requires-Dist: pytest-timeout<3.0,>=2.3; extra == 'dev'
Requires-Dist: pytest<9,>=8.3; extra == 'dev'
Requires-Dist: pytype>=2024.4.11; extra == 'dev'
Requires-Dist: reuse<6.0.0,>=4.0.0; extra == 'dev'
Requires-Dist: ruff<1.0,>=0.6.9; extra == 'dev'
Requires-Dist: schemathesis<4.0,>=3.29; extra == 'dev'
Requires-Dist: twine<7.0,>=6.1.0; extra == 'dev'
Requires-Dist: types-pyyaml<7.0,>=6.0.12; extra == 'dev'
Requires-Dist: typing-extensions<5,>=4.9; extra == 'dev'
Requires-Dist: vulture<3.0,>=2.7; extra == 'dev'
Provides-Extra: docs
Requires-Dist: mkdocs-click<1,>=0.8; extra == 'docs'
Requires-Dist: mkdocs-gen-files<1,>=0.5; extra == 'docs'
Requires-Dist: mkdocs-git-revision-date-localized-plugin<2,>=1.2; extra == 'docs'
Requires-Dist: mkdocs-glightbox>=0.4.0; extra == 'docs'
Requires-Dist: mkdocs-literate-nav<1,>=0.6; extra == 'docs'
Requires-Dist: mkdocs-material<10,>=9.5; extra == 'docs'
Requires-Dist: mkdocs-minify-plugin<1,>=0.8; extra == 'docs'
Requires-Dist: mkdocs-redirects<2,>=1.2; extra == 'docs'
Requires-Dist: mkdocs-section-index<1,>=0.3; extra == 'docs'
Requires-Dist: mkdocs<2,>=1.6; extra == 'docs'
Requires-Dist: mkdocstrings[python]<1,>=0.29; extra == 'docs'
Requires-Dist: pymdown-extensions<11,>=10.8; extra == 'docs'
